MANIFEST.in
setup.cfg
setup.py
pybcs/__init__.py
pybcs/__init__.pyc
pybcs/bcs.py
pybcs/bcs.pyc
pybcs/bucket.py
pybcs/bucket.pyc
pybcs/common.py
pybcs/common.pyc
pybcs/config.pyc
pybcs/httpc.py
pybcs/httpc.pyc
pybcs/object.py
pybcs/object.pyc
pybcs.egg-info/PKG-INFO
pybcs.egg-info/SOURCES.txt
pybcs.egg-info/dependency_links.txt
pybcs.egg-info/requires.txt
pybcs.egg-info/top_level.txt
test/test_bcsh.py
test/test_pybcs.py
tools/bcsh.py